skultrafast/__init__.py
skultrafast/_version.py
skultrafast/base_functions.py
skultrafast/data_io.py
skultrafast/dataset.py
skultrafast/dv.py
skultrafast/filter.py
skultrafast/fit_spectrum.py
skultrafast/fitter.py
skultrafast/kinetic_model.py
skultrafast/lifetimemap.py
skultrafast/messpy.py
skultrafast/nlo.py
skultrafast/pfid_fitter.py
skultrafast/plot_helpers.py
skultrafast/quickcontrol.py
skultrafast/single_spectrum.py
skultrafast/styles.py
skultrafast/sympy_model.py
skultrafast/twoD_dataset.py
skultrafast/twoD_plotter.py
skultrafast/unit_conversions.py
skultrafast/utils.py
skultrafast/zero_finding.py
skultrafast/base_funcs/__init__.py
skultrafast/base_funcs/ana.py
skultrafast/base_funcs/backend_tester.py
skultrafast/base_funcs/base_functions_np.py
skultrafast/base_funcs/base_functions_numba.py
skultrafast/base_funcs/lineshapes.py
skultrafast/base_funcs/pytorch_fitter.py
skultrafast/examples/README.rst
skultrafast/examples/convolution.py
skultrafast/examples/tutorial_2d.py
skultrafast/examples/tutorial_compart_modeling.py
skultrafast/examples/tutorial_figures.py
skultrafast/examples/tutorial_fit_pfid.py
skultrafast/examples/tutorial_messpy.py
skultrafast/examples/tutorial_pfid.py
skultrafast/examples/tutorial_spectrometer_calibration.py
skultrafast/examples/tutorial_start.py
skultrafast/examples/tutorial_sys_response_ir.py
skultrafast/examples/wip_fit_pfid.py
skultrafast/examples/wip_messpy25.py
skultrafast/examples/data/PolystyreneFilm_spectrum.npz
skultrafast/examples/data/germanium.npz
skultrafast/examples/data/ir_waterabs.npy
skultrafast/examples/data/messpyv1_data.npz
skultrafast/examples/data/quickcontrol.zip
skultrafast/examples/data/test.npz
skultrafast/tests/__init__.py
skultrafast/tests/test_basefuncs.py
skultrafast/tests/test_data_io.py
skultrafast/tests/test_dataset.py
skultrafast/tests/test_helpers.py
skultrafast/tests/test_imports.py
skultrafast/tests/test_messpy.py
skultrafast/tests/test_plot_helpers.py
skultrafast/tests/test_quickcontrol.py
skultrafast-4.2.dist-info/LICENSE
skultrafast-4.2.dist-info/METADATA
skultrafast-4.2.dist-info/WHEEL
skultrafast-4.2.dist-info/top_level.txt
skultrafast-4.2.dist-info/RECORD
