Metadata-Version: 2.1
Name: skultrafast
Version: 4.2
Summary: Python package for analyzing time-resolved spectra.
Home-page: http://github.com/tillsten/skultrafast
Author: Till Stensitzki
Author-email: tillsten@zedat.fu-berlin.de
License: LICENSE.txt
Keywords: science physics chemistry pump-probe spectroscopy time-resolved
Requires-Python: >=3.9
License-File: LICENSE
Requires-Dist: attrs
Requires-Dist: numpy
Requires-Dist: scipy
Requires-Dist: lmfit
Requires-Dist: numba
Requires-Dist: scikit-learn
Requires-Dist: matplotlib
Requires-Dist: pytest
Requires-Dist: sympy
Requires-Dist: wrapt
Requires-Dist: zipfile-deflate64
Requires-Dist: h5py
